xrft/__init__.py
xrft/_version.py
xrft/detrend.py
xrft/padding.py
xrft/utils.py
xrft/xrft.py
xrft/tests/__init__.py
xrft/tests/test_detrend.py
xrft/tests/test_padding.py
xrft/tests/test_utils.py
xrft/tests/test_xrft.py
xrft-1.0.1.dist-info/LICENSE
xrft-1.0.1.dist-info/METADATA
xrft-1.0.1.dist-info/WHEEL
xrft-1.0.1.dist-info/top_level.txt
xrft-1.0.1.dist-info/RECORD
