Metadata-Version: 2.1
Name: xrft
Version: 1.0.1
Summary: Discrete Fourier Transform with xarray
Home-page: https://github.com/xgcm/xrft
Author: xrft Developers
Author-email: takaya.uchida@univ-grenoble-alpes.fr
License: MIT
Project-URL: Documentation, https://xrft.readthedocs.io/en/latest/
Project-URL: Source, https://github.com/xgcm/xrft
Project-URL: Tracker, https://github.com/xgcm/xrft/issues
Classifier: Development Status :: 5 - Production/Stable
Classifier: Intended Audience :: Science/Research
Classifier: License :: OSI Approved :: MIT License
Classifier: Natural Language :: English
Classifier: Operating System :: OS Independent
Classifier: Programming Language :: Python :: 3.6
Classifier: Programming Language :: Python :: 3.7
Classifier: Programming Language :: Python :: 3.8
Classifier: Programming Language :: Python :: 3.9
Classifier: Topic :: Scientific/Engineering
Requires-Python: >=3.6
License-File: LICENSE
Requires-Dist: xarray
Requires-Dist: dask
Requires-Dist: numpy
Requires-Dist: pandas
Requires-Dist: scipy
Provides-Extra: agg
Requires-Dist: numpy-groupies ; extra == 'agg'
Provides-Extra: all
Requires-Dist: cftime ; extra == 'all'
Requires-Dist: numpy-groupies ; extra == 'all'
Requires-Dist: pytest (>=6.2.2) ; extra == 'all'
Requires-Dist: pytest-cov ; extra == 'all'
Provides-Extra: io
Requires-Dist: cftime ; extra == 'io'
Provides-Extra: test
Requires-Dist: pytest (>=6.2.2) ; extra == 'test'
Requires-Dist: pytest-cov ; extra == 'test'
